[
    {
      "id": "1",
      "picture": "https://allresultbd.com/wp-content/uploads/2016/04/ID-Card-Info-Correction.jpg",
      "title": "জাতীয় পরিচয়পত্র সংশোধন",
      "description": "আপনি কি আপনার জাতীয় পরিচয় পত্র NID কার্ড সংশোধন করতে চান ? চলে আসুন মল্লিকা কম্পিউটার এ। উপজেলা গেইট সংলগ্ন, সোনালী ব্যাংকের নিচে, মাদারীপুর সদর, মাদারীপুর। আপনার সকল সহযোগীতা করা জন্য প্রস্তুত। গরীব ও অসহায় লোকদের জন্য বিশেষ ছাড় রয়েছে। শুধু বলতে হবে ভাই আমি গরীব অসহায় আমাকে কিছু ছাড় দিন। ২০% থেকে ৫০% পর্যন্ত ছাড় একমাত্র গরীব ও অসহায় মানুষের জন্য।"
    },
    {
      "id": "2",
      "picture": "https://infotakebd.com/wp-content/uploads/2019/04/%E0%A6%9C%E0%A6%BE%E0%A6%A4%E0%A7%80%E0%A7%9F-%E0%A6%AA%E0%A6%B0%E0%A6%BF%E0%A6%9A%E0%A7%9F%E0%A6%AA%E0%A6%A4%E0%A7%8D%E0%A6%B05_compressed.jpg?v=1613200922",
      "title": "নতুন জাতীয় পরিচয় পত্র নিবন্ধন",
      "description": "আপনার বয়স ১৬ থেকে ১৮ বা তার বেশী? তাহলে আর দেরি না করে আপনি মল্লিকা মম্পিউটার সেন্টার চলে আসুন এবং আপনার জাতীয় পরিচয় পত্র পাওয়ার জন্য নিবন্ধন করে নিন। নতৃুন নিবন্ধন করার জন্য আপনার প্রয়োজনীয় কাগজ পত্রের তালিকা নোট করে নিন। ১) জন্ম নিবন্ধন বাংলা ও ইংরেজী (অনলাইন কপি যদি থাকে ভাল হয়।) ২) রক্ত গ্রুপ জানা থাকতে হবে। ৩) পিতা ও মাতার জাতীয় পরিচয়পত্র যদি থাকে। ৪) শিক্ষাগত যোগ্যতার প্রমান পত্র (যদি থাকে)। ৫) হোল্ডিং নং বাসার সামনে লাগানো থাকে। নিবন্ধনকৃত দলিল পত্র জমা দেওয়ার সময় আরও লাগবে ৬) বিদ্যুৎ বিলের ফটোকপি, ৭) চেয়ারম্যানের কাছ থেকে নাগরিক সনদ। ৭) যদি প্রবাসী হয়ে থাকেন তাহলে চেয়ারম্যান এর কাছ থেকে একটা প্রত্যয়ন পত্র প্রয়োজন হবে।"
    },
    {
      "id": "3",
      "picture": "https://mutation.land.gov.bd/land-portal-assets/images/online_info_img.png",
      "title": "অনলাইন মিউটেশনের আবেদন ও পরামর্শ",
      "description": "আপনি কি জমির, বাড়ীর মিউটেশনের আবেদন করতে চান? মল্লিকা মম্পিউটার আপনাকে সহযোগীতা করার জন্য প্রস্তুত। আপনার সকল  বৈধ কাগজ-পত্র যেমনঃ ১) জমির দলিল, ২) বিআরএস পর্চা, ৩) ভূমি উন্নয়ন কর পরিশোধের রশিদ, ৪) ছবি, ৫) সিগনেচার, ৬) ওয়ারিশ সনদ (প্রযোজ্য ক্ষেত্রে) ।"
    },
    {
      "id": "4",
      "picture": "https://attestationonline.com/cms/uploads/f857915d51debf1a7576e1ee4466c1080a42de71.jpg",
      "title":"লেমিনেশন খুলার উপযুক্ত স্থান",
      "description": "আপনি কি আপনার লেমিনেশন পেপার খুলতে চান? আর নয় ঢাকা, আর নয় বরিশাল আপনার বাড়ীর পাশেই হাতের কাছেই চলে আসুণ মল্লিকা কম্পিউটার সেন্টার। আপনাকে সার্বিক সহযোগীতার জন্য প্রস্তুত। ঠিকানাঃ মাদারীপুর সদর উপজেলা গেইট সংলগ্ন, সোনালী ব্যাংক এর নিচে, কুলপদ্বী, মাদারীপুর ।"
    },
    {
      "id": "5",
      "picture": "https://i.ytimg.com/vi/8KeSINlpQ0c/maxresdefault.jpg",
      "title": "প্রবাসীদের কাগজপত্র ইংরেজীতে ট্রানস্লেট করা হয়",
      "description": "আপনার ভাই, বোন, আত্মীয়স্বন বিদেশে আছে এখন বৈধ কাগজপত্র পাওয়ার জন্য সকল কাগজ পত্র ইংরেজীতে ট্রানস্লেট করতে চান? কোথায় করবেন লোক খুজে পাচ্ছেন না? আমরা আপনাকে সহযোগীতা করা জন্য সর্বদা প্রস্তুত। আপনার কেচ ফাইল ইংরেজীতে রূপান্তর করতে চান চলে আসুন আমাদের কাছে।"
    },
    {
      "id": "6",
      "picture": "https://allresultbd.com/wp-content/uploads/2016/04/ID-Card-Info-Correction.jpg",
      "title": "চাকুরীর আবেদন",
      "description": "যেকোন ধরনের সরকারী বেসরকারী চাকুরীর নির্ভুল আবেদন করার সুষ্ঠ ও মনোরম পরিবেশ মল্লিকা মম্পিউটার।"
    },
    {
      "id": "7",
      "picture": "https://allresultbd.com/wp-content/uploads/2016/04/ID-Card-Info-Correction.jpg",
      "title": 946,
      "description": "Cote Perkins"
    }
  ]